pypeeper/__init__.py
pypeeper/pypeeper.py
pypeeper/pypeeper_3.py
pypeeper/examples/__init__.py
pypeeper/examples/basic_example.py
pypeeper/test/__init__.py
pypeeper/test/test_fun_pypeeper.py
pypeeper-1.1.dist-info/LICENSE.txt
pypeeper-1.1.dist-info/METADATA
pypeeper-1.1.dist-info/WHEEL
pypeeper-1.1.dist-info/top_level.txt
pypeeper-1.1.dist-info/RECORD
