Metadata-Version: 2.1
Name: pypeeper
Version: 1.1
Summary: A minimalist, single-threaded and broadcast-routed observable pattern.
Home-page: https://github.com/rolandshoemaker/py-peeper
Author: Jonatan Rivilla Alamo
Author-email: jonrivala@gmail.com
License: UNKNOWN
Platform: UNKNOWN
Classifier: Programming Language :: Python :: 3
Classifier: License :: OSI Approved :: MIT License
Classifier: Operating System :: OS Independent
